pepperssh/__init__.py
pepperssh/client.py
pepperssh/clientcnxn.py
pepperssh/globs.py
pepperssh/protocol.py
pepperssh/server.py
pepperssh/utils.py
pepperssh-2.3.0.dist-info/LICENSE
pepperssh-2.3.0.dist-info/METADATA
pepperssh-2.3.0.dist-info/WHEEL
pepperssh-2.3.0.dist-info/top_level.txt
pepperssh-2.3.0.dist-info/RECORD
