Metadata-Version: 2.1
Name: pepperssh
Version: 2.3.0
Summary: Simple SSH based remote execution
Home-page: https://gitlab.com/mkleehammer/pepperssh
Author: Michael Kleehammer
Author-email: michael@kleehammer.com
License: UNKNOWN
Platform: UNKNOWN
License-File: LICENSE
